Procesador con mi propio testbench/Acumulador.v
module Acumulador (input clk,eneabled,rst, input [3:0]in, output [3:0]out);
  wire clk,eneabled,rst;
  wire [3:0]in;
  reg [3:0]out=0;
  always @ (posedge clk) //va a funcionar cada vez que reciba un clk o rst
    begin
      if(rst)  // =rst se reiniciara el contador
        begin
          out<= 0;
        end
      else if (eneabled==1) // indica si esta en uso
        begin
          out<=in;
        end
    end
endmodule

Procesador con mi propio testbench/Rom.v
module Rom (input wire [11:0] add, output wire [7:0] data); 

  reg [7:0] mem [0:4095];     
  assign data = mem[add];

  initial begin                       
    $readmemh("memory.list", mem);  
  end

endmodule

Nibbler/Ram.v
module Ram(input [11:0]add, input weRam,csRam, inout [3:0]out);

    wire [11:0]add;   
    wire weRam,csRam;
    reg [3:0] ram [0:4095];
    reg [3:0] data_out;

    assign out = (csRam&&!weRam) ? data_out : 4'bzzzz;

    always @ (add or out or csRam or weRam) 
    begin                                          
      if ((csRam==1) && (weRam==1))               
        begin
          ram[add]<=out;
        end
      else if ((csRam==1)&&(weRam==0)) 
        begin
          data_out<=ram[add];
        end
    end


endmodule

Nibbler/Phase_module.v
module Phase_module (input clk,rst, output out); 

reg out = 0;      

always @ (posedge clk)
  begin
    out <= ~out;      
  end

endmodule

Procesador con mi propio testbench/P_counter.v
module P_counter(input clk,enabled,rst,load, input [11:0]in, output [11:0]C); 

  wire clk,enabled,rst,load; 
  wire [11:0]in;
  reg [11:0]C=0;

  always @ (posedge clk)    
    begin
      if (load) 
        begin     
          C <= in;
        end
      else if(rst) 
        begin    
          C <= 0;
        end
      else if (enabled) 
        begin    
          C <= C+1;
        end
    end

endmodule

Procesador con mi propio testbench/Flags.v
module Flags (input clk,enabled,rst,C,Zeta, output C_out,Zeta_out); 

  wire clk,enabled,rst,C,Zeta;    
  reg C_out=0;
  reg Zeta_out=0;

  always @ (posedge clk)
    begin
      if(rst) 
        begin        
          C_out <= 0;
          Zeta_out <= 0;
        end
      else if (enabled==1) 
        begin       
          C_out <=  C;
          Zeta_out <=  Zeta;
        end
    end

endmodule

Nibbler/Fetch.v
module Fetch (input clk,enabled,rst, input [7:0]D_in, output [7:0]D_out); 

  wire clk,enabled,rst; 
  wire [7:0]D_in;
  reg [7:0]D_out=0;

  always @ (posedge clk or posedge rst)
    begin
      if(rst) 
        begin           
          D_out <= 0;
        end
      else if (enabled) 
        begin    
          D_out <= D_in;
        end
    end

endmodule

Procesador con mi propio testbench/Decoder.v
module Decoder(input phase,C,Zeta, input [3:0]in, output [12:0]out);
  wire phase,C,Zeta;
  wire [3:0]in;
  reg [12:0]carry=0;
  assign out = carry;
  always @ (phase or C or Zeta or in)
  begin
    if (phase==0)
      begin                               // ANY //
        carry  = 13'b1000000001000;
      end
    else
      begin
        if (in==4'b0000 && C==1)
          begin
            carry  <= 13'b0100000001000;    // JC CARRY_1//
          end
        else if (in==4'b0000 && C==0)
          begin
            carry  = 13'b1000000001000;     //JC CARRY_0
          end
        else if (in==4'b0001 && C==1)
          begin
            carry  = 13'b1000000001000;     //JNC  CARRY _1
          end
        else if (in==4'b0001 && C==0)
          begin
            carry  = 13'b0100000001000;     //JNC  CARRY_0
          end
        else if (in==4'b0010)
          begin
            carry  = 13'b0001001000010;     // CMPI
          end
        else if (in==4'b0011)
          begin
            carry  = 13'b1001001100000;   // CMPM
          end
        else if (in==4'b0100)
          begin
            carry  = 13'b0011010000010;   // LIT
          end
        else if (in==4'b0101)
          begin
            carry  = 13'b0011010000100;   // IN
          end
        else if (in==4'b0110)
          begin
            carry  = 13'b1011010100000;   // LD
          end
        else if (in==4'b0111)
          begin
            carry  = 13'b1000000111000;   //ST
          end
        else if (in==4'b1000 && Zeta==1)
          begin
            carry  = 13'b0100000001000;   //JZ Z_1
          end
        else if (in==4'b1000 && Zeta==0)
          begin
            carry  = 13'b1000000001000;   //JZ Z_0
          end
        else if (in==4'b1001 && Zeta==1)
          begin
            carry  = 13'b1000000001000;   // JNZ Z_1
          end
        else if (in==4'b1001 && Zeta==0)
          begin
            carry  = 13'b0100000001000;   // JNZ Z_0
          end
        else if (in==4'b1010)
          begin
            carry  = 13'b0011011000010;   // ADDI
          end
        else if (in==4'b1011)
          begin
            carry  = 13'b1011011100000;   // ADDM
          end
        else if (in==4'b1100)
          begin
            carry  = 13'b0100000001000;   // JMP
          end
        else if (in==4'b1101)
          begin
            carry  = 13'b0000000001001;   //OUT
          end
        else if (in==4'b1110)
          begin
            carry  = 13'b0011100000010;   //NANDI
          end
        else if (in==4'b1111)
          begin
            carry  = 13'b1011100100000;   //NANDM
          end
      end
  end
endmodule

Procesador con mi propio testbench/Buffer.v
module Buffer(input eneabled, input [3:0]in, output [3:0]out);
  wire eneabled;
  wire [3:0]in;
  reg [3:0]out;
  always @ (*)
  begin
    if (eneabled)
      begin
        out[3:0]<=in[3:0];
      end
    else
      begin
        out[3:0]<=4'bzzzz;
      end
  end
endmodule

Procesador con mi propio testbench/Alu.v
module Alu(input [2:0]S, input [3:0]A,B, output C,Zeta, output [3:0]Y);    

  wire [2:0]S;                     
  wire [3:0]A,B;
  reg [3:0]Y;
  reg C=0;
  reg Zeta=0;

  always @ (*)            
    begin                 
      if(S==0)  // si es 000 su salida es A
        begin            
          Y<=A;
          C<=0;
          Zeta= (Y == 0);
        end
      else if (S==2)  // si es 001 su salida es B 
        begin                
          Y<=B;
          C<=0;
          Zeta= (Y == 0);
        end
      else if (S==3)  // si es 010 su salida es la suma de A y B, si existe un overflow agrega un 1 y si no es asi se mantiene en 0
        begin               
          Y<=(A+B);
          Zeta= (Y == 0);
              if((A+B)>15)   
              begin
                C<=1;
              end
            else          
              begin
                C<=0;
              end
        end
      else if (S==1)  // si es 011 compara A y B
        begin             
          Y<=(A-B);
          if (A==B) 
            begin
              Zeta = (Y == 0);         
              C<=0;
            end
          else if (A>B) 
            begin
              Zeta= (Y == 0);
              C<=0;
            end
          else 
            begin
              C<=1;
              Zeta= (Y == 0);
            end
        end
      else if (S==4)         
        begin
          Y<=(~(A&B));    
          C<=0;
          Zeta= (Y == 0);
        end
      else 
        begin
          Y<=Y;     
          C<=0;
          Zeta= (Y == 0);
        end
    end

endmodule

Procesador con mi propio testbench/uP.v
module uP( input clock,reset, input [3:0]pushbuttons, output phase,c_flag,z_flag, output [3:0] instr,oprnd,data_bus,FF_out,accu, output [7:0] program_byte, output [11:0] PC, address_RAM);
  /*instr es la salida del fetch con bits mas significativos
  oprnd es la salida del fetch con bits menos significativos
  data_bus 1 es la salida del buffer 1
  FF_out es la salida del flip flop 
  accu es la salida del acumulador
  program byte es la salida del rom
  pc es la salida de el program counter*/

    wire [2:0]Y;
    wire [3:0]ALU_out;
    wire [7:0]out_fetch;
    wire [12:0]dato_out;
    wire incPC,loadPC,loadA,loadflags,csRAM,weRAM,oeALU,oeIN,oeOprnd,loadOut,C,Zeta;
    assign address_RAM[11:8] = oprnd;
    assign address_RAM[7:0] = program_byte;
    assign csRAM = dato_out[5];
    assign instr = out_fetch[7:4]; 
    assign incPC = dato_out[12];
    assign loadA = dato_out[10];
    assign loadflags = dato_out[9];
    assign loadOut = dato_out[0];
    assign loadPC = dato_out[11];
    assign oprnd = out_fetch[3:0];
    assign oeALU = dato_out[3];
    assign oeIN = dato_out[2];
    assign oeOprnd = dato_out[1];
    assign Y = dato_out[8:6];
    assign weRAM = dato_out[4];

  Acumulador       accumulator (clock,loadA,reset,ALU_out,accu);
  Alu              alu (Y,accu,data_bus,C,Zeta,ALU_out);
  Buffer           buffer_alu (oeALU,ALU_out,data_bus);
  Buffer           buffer_fetch (oeOprnd,oprnd,data_bus);
  Buffer           buffer_in (oeIN,pushbuttons,data_bus);
  Decoder          decoder (phase,c_flag,z_flag,instr,dato_out);
  Fetch            fetch  (clock,~phase,reset,program_byte,out_fetch);
  Flags            flags_module (clock,loadflags,reset,C,Zeta,c_flag,z_flag);
  P_counter        program_counter (clock,incPC,reset,loadPC,address_RAM,PC);
  Phase_module     Phase_module (clock,reset,phase);
  Ram              ram (address_RAM,weRAM,csRAM,data_bus);
  Rom              rom (PC,program_byte);
  Acumulador       ffout (clock,loadOut,reset,data_bus,FF_out);

endmodule

`include "Acumulador.v"
`include "Alu.v"
`include "Buffer.v"
`include "Decoder.v"
`include "Fetch.v"
`include "Flags.v"
`include "P_counter.v"
`include "Phase_module.v"
`include "Ram.v"
`include "Rom.v"

Procesador con mi propio testbench/uP_tb.v
`include "uP.v"
module testbench();

    reg clock, reset;
    reg [3:0] pushbuttons;
    wire phase, c_flag, z_flag;
    wire [3:0] instr, oprnd, accu, data_bus, FF_out;
    wire [7:0] program_byte;
    wire [11:0] PC, address_RAM;


    uP uPmodule(.clock(clock),
                .reset(reset),
                .pushbuttons(pushbuttons),
                .phase(phase),
                .c_flag(c_flag),
                .z_flag(z_flag),
                .instr(instr),
                .oprnd(oprnd),
                .accu(accu),
                .data_bus(data_bus),
                .FF_out(FF_out),
                .program_byte(program_byte),
                .PC(PC),
                .address_RAM(address_RAM));

    initial
        #650 $finish;

    always
        #5 clock = ~clock;

    initial 
    begin
        clock = 0;  reset = 1;pushbuttons = 4'b010; 
        #2 reset = 0;
    end

    initial 
    begin
        $dumpfile("uP_tb.vcd");
        $dumpvars(0, testbench);
    end


endmodule

Procesador con mi propio testbench/uP_tb.vcd
$date
	Sun Nov 22 11:45:28 2020
$end
$version
	Icarus Verilog
$end
$timescale
	1s
$end
$scope module testbench $end
$var wire 4 ! data_bus [3:0] $end
$var wire 1 " z_flag $end
$var wire 8 # program_byte [7:0] $end
$var wire 1 $ phase $end
$var wire 4 % oprnd [3:0] $end
$var wire 4 & instr [3:0] $end
$var wire 1 ' c_flag $end
$var wire 12 ( address_RAM [11:0] $end
$var wire 4 ) accu [3:0] $end
$var wire 12 * PC [11:0] $end
$var wire 4 + FF_out [3:0] $end
$var reg 1 , clock $end
$var reg 4 - pushbuttons [3:0] $end
$var reg 1 . reset $end
$scope module uPmodule $end
$var wire 1 , clock $end
$var wire 4 / data_bus [3:0] $end
$var wire 4 0 pushbuttons [3:0] $end
$var wire 1 . reset $end
$var wire 1 " z_flag $end
$var wire 1 1 weRAM $end
$var wire 8 2 program_byte [7:0] $end
$var wire 1 $ phase $end
$var wire 8 3 out_fetch [7:0] $end
$var wire 4 4 oprnd [3:0] $end
$var wire 1 5 oeOprnd $end
$var wire 1 6 oeIN $end
$var wire 1 7 oeALU $end
$var wire 1 8 loadflags $end
$var wire 1 9 loadPC $end
$var wire 1 : loadOut $end
$var wire 1 ; loadA $end
$var wire 4 < instr [3:0] $end
$var wire 1 = incPC $end
$var wire 13 > dato_out [12:0] $end
$var wire 1 ? csRAM $end
$var wire 1 ' c_flag $end
$var wire 12 @ address_RAM [11:0] $end
$var wire 4 A accu [3:0] $end
$var wire 1 B Zeta $end
$var wire 3 C Y [2:0] $end
$var wire 12 D PC [11:0] $end
$var wire 4 E FF_out [3:0] $end
$var wire 1 F C $end
$var wire 4 G ALU_out [3:0] $end
$scope module Phase_module $end
$var wire 1 , clk $end
$var wire 1 . rst $end
$var reg 1 $ out $end
$upscope $end
$scope module accumulator $end
$var wire 1 , clk $end
$var wire 1 ; eneabled $end
$var wire 1 . rst $end
$var wire 4 H in [3:0] $end
$var reg 4 I out [3:0] $end
$upscope $end
$scope module alu $end
$var wire 4 J A [3:0] $end
$var wire 4 K B [3:0] $end
$var wire 3 L S [2:0] $end
$var reg 1 F C $end
$var reg 4 M Y [3:0] $end
$var reg 1 B Zeta $end
$upscope $end
$scope module buffer_alu $end
$var wire 1 7 eneabled $end
$var wire 4 N in [3:0] $end
$var reg 4 O out [3:0] $end
$upscope $end
$scope module buffer_fetch $end
$var wire 1 5 eneabled $end
$var wire 4 P in [3:0] $end
$var reg 4 Q out [3:0] $end
$upscope $end
$scope module buffer_in $end
$var wire 1 6 eneabled $end
$var wire 4 R in [3:0] $end
$var reg 4 S out [3:0] $end
$upscope $end
$scope module decoder $end
$var wire 4 T in [3:0] $end
$var wire 13 U out [12:0] $end
$var wire 1 $ phase $end
$var wire 1 " Zeta $end
$var wire 1 ' C $end
$var reg 13 V carry [12:0] $end
$upscope $end
$scope module fetch $end
$var wire 1 , clk $end
$var wire 1 W enabled $end
$var wire 1 . rst $end
$var wire 8 X D_in [7:0] $end
$var reg 8 Y D_out [7:0] $end
$upscope $end
$scope module ffout $end
$var wire 1 , clk $end
$var wire 1 : eneabled $end
$var wire 4 Z in [3:0] $end
$var wire 1 . rst $end
$var reg 4 [ out [3:0] $end
$upscope $end
$scope module flags_module $end
$var wire 1 F C $end
$var wire 1 B Zeta $end
$var wire 1 , clk $end
$var wire 1 8 enabled $end
$var wire 1 . rst $end
$var reg 1 ' C_out $end
$var reg 1 " Zeta_out $end
$upscope $end
$scope module program_counter $end
$var wire 1 , clk $end
$var wire 1 = enabled $end
$var wire 12 \ in [11:0] $end
$var wire 1 9 load $end
$var wire 1 . rst $end
$var reg 12 ] C [11:0] $end
$upscope $end
$scope module ram $end
$var wire 12 ^ add [11:0] $end
$var wire 1 ? csRam $end
$var wire 4 _ out [3:0] $end
$var wire 1 1 weRam $end
$var reg 4 ` data_out [3:0] $end
$upscope $end
$scope module rom $end
$var wire 12 a add [11:0] $end
$var wire 8 b data [7:0] $end
$upscope $end
$upscope $end
$upscope $end
$enddefinitions $end
#0
$dumpvars
b1001111 b
b0 a
bx `
b0 _
b1001111 ^
b0 ]
b1001111 \
b0 [
b0 Z
b0 Y
b1001111 X
1W
b1000000001000 V
b1000000001000 U
b0 T
bz S
b10 R
bz Q
b0 P
b0 O
b0 N
b0 M
b0 L
b0 K
b0 J
b0 I
b0 H
b0 G
0F
b0 E
b0 D
b0 C
1B
b0 A
b1001111 @
0?
b1000000001000 >
1=
b0 <
0;
0:
09
08
17
06
05
b0 4
b0 3
b1001111 2
01
b10 0
b0 /
1.
b10 -
0,
b0 +
b0 *
b0 )
b1001111 (
0'
b0 &
b0 %
0$
b1001111 #
0"
b0 !
$end
#2
0.
#5
0B
b1111 G
b1111 H
b1111 M
b1111 N
b1111 Q
b1111 !
b1111 /
b1111 K
b1111 Z
b1111 _
bz O
b10 C
b10 L
15
07
18
1;
0=
b11010000010 >
b11010000010 U
b11010000010 V
0W
b1111 %
b1111 4
b1111 P
b100 &
b100 <
b100 T
b111111011111 (
b111111011111 @
b111111011111 \
b111111011111 ^
b11011111 #
b11011111 2
b11011111 X
b11011111 b
b1 *
b1 D
b1 ]
b1 a
1$
b1001111 3
b1001111 Y
1,
#10
0,
#15
bz Q
b1111 O
b0 C
b0 L
05
17
08
0;
1=
b1000000001000 >
b1000000001000 U
b1000000001000 V
1W
0$
b1111 )
b1111 A
b1111 I
b1111 J
1,
#20
0,
#25
1:
0=
b1001 >
b1001 U
b1001 V
0W
b1101 &
b1101 <
b1101 T
b111101010001 (
b111101010001 @
b111101010001 \
b111101010001 ^
b1010001 #
b1010001 2
b1010001 X
b1010001 b
b10 *
b10 D
b10 ]
b10 a
1$
b11011111 3
b11011111 Y
1,
#30
0,
#35
0:
1=
b1000000001000 >
b1000000001000 U
b1000000001000 V
1W
b1111 +
b1111 E
b1111 [
0$
1,
#40
0,
#45
b10 G
b10 H
b10 M
b10 N
b10 S
b10 !
b10 /
b10 K
b10 Z
b10 _
bz O
b10 C
b10 L
16
07
18
1;
0=
b11010000100 >
b11010000100 U
b11010000100 V
0W
b1 %
b1 4
b1 P
b101 &
b101 <
b101 T
b101000000 (
b101000000 @
b101000000 \
b101000000 ^
b1000000 #
b1000000 2
b1000000 X
b1000000 b
b11 *
b11 D
b11 ]
b11 a
1$
b1010001 3
b1010001 Y
1,
#50
0,
#55
bz S
b10 O
b0 C
b0 L
06
17
08
0;
1=
b1000000001000 >
b1000000001000 U
b1000000001000 V
1W
0$
b10 )
b10 A
b10 I
b10 J
1,
#60
0,
#65
1B
b0 G
b0 H
b0 M
b0 N
b0 Q
b0 !
b0 /
b0 K
b0 Z
b0 _
bz O
b10 C
b10 L
15
07
18
1;
0=
b11010000010 >
b11010000010 U
b11010000010 V
0W
b0 %
b0 4
b0 P
b100 &
b100 <
b100 T
b1001111 (
b1001111 @
b1001111 \
b1001111 ^
b1001111 #
b1001111 2
b1001111 X
b1001111 b
b100 *
b100 D
b100 ]
b100 a
1$
b1000000 3
b1000000 Y
1,
#70
0,
#75
bz Q
b0 O
b0 C
b0 L
05
17
08
0;
1=
1W
b1000000001000 >
b1000000001000 U
b1000000001000 V
0$
1"
b0 )
b0 A
b0 I
b0 J
1,
#80
0,
#85
0B
b1111 G
b1111 H
b1111 M
b1111 N
b1111 Q
b1111 !
b1111 /
b1111 K
b1111 Z
b1111 _
bz O
b10 C
b10 L
15
07
18
1;
0=
b11010000010 >
b11010000010 U
b11010000010 V
0W
b1111 %
b1111 4
b1111 P
b111110101010 (
b111110101010 @
b111110101010 \
b111110101010 ^
b10101010 #
b10101010 2
b10101010 X
b10101010 b
b101 *
b101 D
b101 ]
b101 a
1$
b1001111 3
b1001111 Y
1,
#90
0,
#95
bz Q
b1111 O
b0 C
b0 L
05
17
08
0;
1=
1W
b1000000001000 >
b1000000001000 U
b1000000001000 V
0$
0"
b1111 )
b1111 A
b1111 I
b1111 J
1,
#100
0,
#105
1F
b1001 G
b1001 H
b1001 M
b1001 N
b1010 Q
b1010 !
b1010 /
b1010 K
b1010 Z
b1010 _
bz O
b11 C
b11 L
15
07
18
1;
0=
b11011000010 >
b11011000010 U
b11011000010 V
0W
b1010 %
b1010 4
b1010 P
b1010 &
b1010 <
b1010 T
b101000101000 (
b101000101000 @
b101000101000 \
b101000101000 ^
b101000 #
b101000 2
b101000 X
b101000 b
b110 *
b110 D
b110 ]
b110 a
1$
b10101010 3
b10101010 Y
1,
#110
0,
#115
0F
bz Q
b1001 !
b1001 /
b1001 K
b1001 Z
b1001 _
b1001 O
b1001 G
b1001 H
b1001 M
b1001 N
b0 C
b0 L
05
17
08
0;
1=
1W
b1000000001000 >
b1000000001000 U
b1000000001000 V
0$
1'
b1001 )
b1001 A
b1001 I
b1001 J
1,
#120
0,
#125
0B
b1 G
b1 H
b1 M
b1 N
b1000 Q
b1000 !
b1000 /
b1000 K
b1000 Z
b1000 _
bz O
b1 C
b1 L
15
07
18
0=
b1001000010 >
b1001000010 U
b1001000010 V
0W
b1000 %
b1000 4
b1000 P
b10 &
b10 <
b10 T
b100001001010 (
b100001001010 @
b100001001010 \
b100001001010 ^
b1001010 #
b1001010 2
b1001010 X
b1001010 b
b111 *
b111 D
b111 ]
b111 a
1$
b101000 3
b101000 Y
1,
#130
0,
#135
b1001 G
b1001 H
b1001 M
b1001 N
bz Q
b1001 !
b1001 /
b1001 K
b1001 Z
b1001 _
b1001 O
b0 C
b0 L
05
17
08
1=
1W
b1000000001000 >
b1000000001000 U
b1000000001000 V
0$
0'
1,
#140
0,
#145
b1010 G
b1010 H
b1010 M
b1010 N
b1010 Q
b1010 !
b1010 /
b1010 K
b1010 Z
b1010 _
bz O
b10 C
b10 L
15
07
18
1;
0=
b11010000010 >
b11010000010 U
b11010000010 V
0W
b1010 %
b1010 4
b1010 P
b100 &
b100 <
b100 T
b101000101100 (
b101000101100 @
b101000101100 \
b101000101100 ^
b101100 #
b101100 2
b101100 X
b101100 b
b1000 *
b1000 D
b1000 ]
b1000 a
1$
b1001010 3
b1001010 Y
1,
#150
0,
#155
bz Q
b1010 O
b0 C
b0 L
05
17
08
0;
1=
b1000000001000 >
b1000000001000 U
b1000000001000 V
1W
0$
b1010 )
b1010 A
b1010 I
b1010 J
1,
#160
0,
#165
1F
0B
b1110 G
b1110 H
b1110 M
b1110 N
b1100 Q
b1100 !
b1100 /
b1100 K
b1100 Z
b1100 _
bz O
b1 C
b1 L
15
07
18
0=
b1001000010 >
b1001000010 U
b1001000010 V
0W
b1100 %
b1100 4
b1100 P
b10 &
b10 <
b10 T
b110010100001 (
b110010100001 @
b110010100001 \
b110010100001 ^
b10100001 #
b10100001 2
b10100001 X
b10100001 b
b1001 *
b1001 D
b1001 ]
b1001 a
1$
b101100 3
b101100 Y
1,
#170
0,
#175
0F
b1010 G
b1010 H
b1010 M
b1010 N
bz Q
b1010 !
b1010 /
b1010 K
b1010 Z
b1010 _
b1010 O
b0 C
b0 L
05
17
08
1=
1W
b1000000001000 >
b1000000001000 U
b1000000001000 V
0$
1'
1,
#180
0,
#185
0F
b1011 G
b1011 H
b1011 M
b1011 N
b1 Q
b1 !
b1 /
b1 K
b1 Z
b1 _
bz O
b11 C
b11 L
15
07
18
1;
0=
b11011000010 >
b11011000010 U
b11011000010 V
0W
b1 %
b1 4
b1 P
b1010 &
b1010 <
b1010 T
b111101011 (
b111101011 @
b111101011 \
b111101011 ^
b11101011 #
b11101011 2
b11101011 X
b11101011 b
b1010 *
b1010 D
b1010 ]
b1010 a
1$
b10100001 3
b10100001 Y
1,
#190
0,
#195
bz Q
b1011 !
b1011 /
b1011 K
b1011 Z
b1011 _
b1011 O
b1011 G
b1011 H
b1011 M
b1011 N
b0 C
b0 L
05
17
08
0;
1=
1W
b1000000001000 >
b1000000001000 U
b1000000001000 V
0$
0'
b1011 )
b1011 A
b1011 I
b1011 J
1,
#200
0,
#205
b100 G
b100 H
b100 M
b100 N
b1011 Q
b1011 !
b1011 /
b1011 K
b1011 Z
b1011 _
bz O
b100 C
b100 L
15
07
18
1;
0=
b11100000010 >
b11100000010 U
b11100000010 V
0W
b1011 %
b1011 4
b1011 P
b1110 &
b1110 <
b1110 T
b101111010000 (
b101111010000 @
b101111010000 \
b101111010000 ^
b11010000 #
b11010000 2
b11010000 X
b11010000 b
b1011 *
b1011 D
b1011 ]
b1011 a
1$
b11101011 3
b11101011 Y
1,
#210
0,
#215
bz Q
b100 !
b100 /
b100 K
b100 Z
b100 _
b100 O
b100 G
b100 H
b100 M
b100 N
b0 C
b0 L
05
17
08
0;
1=
b1000000001000 >
b1000000001000 U
b1000000001000 V
1W
0$
b100 )
b100 A
b100 I
b100 J
1,
#220
0,
#225
1:
0=
b1001 >
b1001 U
b1001 V
0W
b0 %
b0 4
b0 P
b1101 &
b1101 <
b1101 T
b1010000 (
b1010000 @
b1010000 \
b1010000 ^
b1010000 #
b1010000 2
b1010000 X
b1010000 b
b1100 *
b1100 D
b1100 ]
b1100 a
1$
b11010000 3
b11010000 Y
1,
#230
0,
#235
0:
1=
b1000000001000 >
b1000000001000 U
b1000000001000 V
1W
b100 +
b100 E
b100 [
0$
1,
#240
0,
#245
b10 G
b10 H
b10 M
b10 N
b10 S
b10 !
b10 /
b10 K
b10 Z
b10 _
bz O
b10 C
b10 L
16
07
18
1;
0=
b11010000100 >
b11010000100 U
b11010000100 V
0W
b101 &
b101 <
b101 T
b1110000 (
b1110000 @
b1110000 \
b1110000 ^
b1110000 #
b1110000 2
b1110000 X
b1110000 b
b1101 *
b1101 D
b1101 ]
b1101 a
1$
b1010000 3
b1010000 Y
1,
#250
0,
#255
bz S
b10 O
b0 C
b0 L
06
17
08
0;
1=
b1000000001000 >
b1000000001000 U
b1000000001000 V
1W
0$
b10 )
b10 A
b10 I
b10 J
1,
#260
0,
#265
11
1?
b1000000111000 >
b1000000111000 U
b1000000111000 V
0W
b111 &
b111 <
b111 T
b0 (
b0 @
b0 \
b0 ^
b0 #
b0 2
b0 X
b0 b
b1110 *
b1110 D
b1110 ]
b1110 a
1$
b1110000 3
b1110000 Y
1,
#270
0,
#275
01
0?
b1000000001000 >
b1000000001000 U
b1000000001000 V
1W
0$
b1001111 (
b1001111 @
b1001111 \
b1001111 ^
b1001111 #
b1001111 2
b1001111 X
b1001111 b
b1111 *
b1111 D
b1111 ]
b1111 a
1,
#280
0,
#285
b1111 G
b1111 H
b1111 M
b1111 N
b1111 Q
b1111 !
b1111 /
b1111 K
b1111 Z
b1111 _
bz O
b10 C
b10 L
15
07
18
1;
0=
b11010000010 >
b11010000010 U
b11010000010 V
0W
b1111 %
b1111 4
b1111 P
b100 &
b100 <
b100 T
b111101110001 (
b111101110001 @
b111101110001 \
b111101110001 ^
b1110001 #
b1110001 2
b1110001 X
b1110001 b
b10000 *
b10000 D
b10000 ]
b10000 a
1$
b1001111 3
b1001111 Y
1,
#290
0,
#295
bz Q
b1111 O
b0 C
b0 L
05
17
08
0;
1=
b1000000001000 >
b1000000001000 U
b1000000001000 V
1W
0$
b1111 )
b1111 A
b1111 I
b1111 J
1,
#300
0,
#305
11
1?
b1000000111000 >
b1000000111000 U
b1000000111000 V
0W
b1 %
b1 4
b1 P
b111 &
b111 <
b111 T
b100010001 (
b100010001 @
b100010001 \
b100010001 ^
b10001 #
b10001 2
b10001 X
b10001 b
b10001 *
b10001 D
b10001 ]
b10001 a
1$
b1110001 3
b1110001 Y
1,
#310
0,
#315
01
0?
b1000000001000 >
b1000000001000 U
b1000000001000 V
1W
0$
b101001010 (
b101001010 @
b101001010 \
b101001010 ^
b1001010 #
b1001010 2
b1001010 X
b1001010 b
b10010 *
b10010 D
b10010 ]
b10010 a
1,
#320
0,
#325
b1010 G
b1010 H
b1010 M
b1010 N
b1010 Q
b1010 !
b1010 /
b1010 K
b1010 Z
b1010 _
bz O
b10 C
b10 L
15
07
18
1;
0=
b11010000010 >
b11010000010 U
b11010000010 V
0W
b1010 %
b1010 4
b1010 P
b100 &
b100 <
b100 T
b101001110010 (
b101001110010 @
b101001110010 \
b101001110010 ^
b1110010 #
b1110010 2
b1110010 X
b1110010 b
b10011 *
b10011 D
b10011 ]
b10011 a
1$
b1001010 3
b1001010 Y
1,
#330
0,
#335
bz Q
b1010 O
b0 C
b0 L
05
17
08
0;
1=
b1000000001000 >
b1000000001000 U
b1000000001000 V
1W
0$
b1010 )
b1010 A
b1010 I
b1010 J
1,
#340
0,
#345
11
1?
b1000000111000 >
b1000000111000 U
b1000000111000 V
0W
b10 %
b10 4
b10 P
b111 &
b111 <
b111 T
b1000100010 (
b1000100010 @
b1000100010 \
b1000100010 ^
b100010 #
b100010 2
b100010 X
b100010 b
b10100 *
b10100 D
b10100 ]
b10100 a
1$
b1110010 3
b1110010 Y
1,
#350
0,
#355
01
0?
b1000000001000 >
b1000000001000 U
b1000000001000 V
1W
0$
b1001000001 (
b1001000001 @
b1001000001 \
b1001000001 ^
b1000001 #
b1000001 2
b1000001 X
b1000001 b
b10101 *
b10101 D
b10101 ]
b10101 a
1,
#360
0,
#365
b1 G
b1 H
b1 M
b1 N
b1 Q
b1 !
b1 /
b1 K
b1 Z
b1 _
bz O
b10 C
b10 L
15
07
18
1;
0=
b11010000010 >
b11010000010 U
b11010000010 V
0W
b1 %
b1 4
b1 P
b100 &
b100 <
b100 T
b101110011 (
b101110011 @
b101110011 \
b101110011 ^
b1110011 #
b1110011 2
b1110011 X
b1110011 b
b10110 *
b10110 D
b10110 ]
b10110 a
1$
b1000001 3
b1000001 Y
1,
#370
0,
#375
bz Q
b1 O
b0 C
b0 L
05
17
08
0;
1=
b1000000001000 >
b1000000001000 U
b1000000001000 V
1W
0$
b1 )
b1 A
b1 I
b1 J
1,
#380
0,
#385
11
1?
b1000000111000 >
b1000000111000 U
b1000000111000 V
0W
b11 %
b11 4
b11 P
b111 &
b111 <
b111 T
b1100110011 (
b1100110011 @
b1100110011 \
b1100110011 ^
b110011 #
b110011 2
b110011 X
b110011 b
b10111 *
b10111 D
b10111 ]
b10111 a
1$
b1110011 3
b1110011 Y
1,
#390
0,
#395
01
0?
b1000000001000 >
b1000000001000 U
b1000000001000 V
1W
0$
b1101100000 (
b1101100000 @
b1101100000 \
b1101100000 ^
b1100000 #
b1100000 2
b1100000 X
b1100000 b
b11000 *
b11000 D
b11000 ]
b11000 a
1,
#400
0,
#405
0B
b10 G
b10 H
b10 M
b10 N
bz O
b10 `
b10 !
b10 /
b10 K
b10 Z
b10 _
b10 C
b10 L
07
18
1;
1?
b1011010100000 >
b1011010100000 U
b1011010100000 V
0W
b0 %
b0 4
b0 P
b110 &
b110 <
b110 T
b0 (
b0 @
b0 \
b0 ^
b0 #
b0 2
b0 X
b0 b
b11001 *
b11001 D
b11001 ]
b11001 a
1$
b1100000 3
b1100000 Y
1,
#410
0,
#415
b10 O
bx `
b10 !
b10 /
b10 K
b10 Z
b10 _
b0 C
b0 L
17
08
0;
0?
b1000000001000 >
b1000000001000 U
b1000000001000 V
1W
0$
b1100001 (
b1100001 @
b1100001 \
b1100001 ^
b1100001 #
b1100001 2
b1100001 X
b1100001 b
b11010 *
b11010 D
b11010 ]
b11010 a
b10 )
b10 A
b10 I
b10 J
1,
#420
0,
#425
0B
b1111 G
b1111 H
b1111 M
b1111 N
bz O
b1111 `
b1111 !
b1111 /
b1111 K
b1111 Z
b1111 _
b10 C
b10 L
07
18
1;
1?
b1011010100000 >
b1011010100000 U
b1011010100000 V
0W
b1 %
b1 4
b1 P
b100010001 (
b100010001 @
b100010001 \
b100010001 ^
b10001 #
b10001 2
b10001 X
b10001 b
b11011 *
b11011 D
b11011 ]
b11011 a
1$
b1100001 3
b1100001 Y
1,
#430
0,
#435
b1111 O
bx `
b1111 !
b1111 /
b1111 K
b1111 Z
b1111 _
b0 C
b0 L
17
08
0;
0?
b1000000001000 >
b1000000001000 U
b1000000001000 V
1W
0$
b101100010 (
b101100010 @
b101100010 \
b101100010 ^
b1100010 #
b1100010 2
b1100010 X
b1100010 b
b11100 *
b11100 D
b11100 ]
b11100 a
b1111 )
b1111 A
b1111 I
b1111 J
1,
#440
0,
